{
  "kind": "Program",
  "body": [
    {
      "kind": "VariableDeclarationStatement",
      "name": "file",
      "isConstant": true,
      "type": {
        "kind": "function",
        "decorators": [
          "intrinsic"
        ],
        "parameters": [
          {
            "name": "path",
            "type": {
              "name": "string",
              "kind": "primitive"
            }
          }
        ],
        "returnType": {
          "name": "string",
          "kind": "primitive"
        }
      },
      "value": {
        "kind": "FunctionDeclarationExpression",
        "type": {
          "kind": "function",
          "decorators": [
            "intrinsic"
          ],
          "parameters": [
            {
              "name": "path",
              "type": {
                "name": "string",
                "kind": "primitive"
              }
            }
          ],
          "returnType": {
            "name": "string",
            "kind": "primitive"
          }
        },
        "body": [],
        "location": {
          "start": 19,
          "end": 45,
          "file": "modules/std.vader"
        }
      },
      "location": {
        "start": 11,
        "end": 45,
        "file": "modules/std.vader"
      }
    },
    {
      "kind": "VariableDeclarationStatement",
      "name": "print",
      "isConstant": true,
      "type": {
        "kind": "function",
        "decorators": [
          "intrinsic"
        ],
        "parameters": [
          {
            "name": "message",
            "type": {
              "name": "string",
              "kind": "primitive"
            }
          }
        ],
        "returnType": {
          "name": "void",
          "kind": "primitive"
        }
      },
      "value": {
        "kind": "FunctionDeclarationExpression",
        "type": {
          "kind": "function",
          "decorators": [
            "intrinsic"
          ],
          "parameters": [
            {
              "name": "message",
              "type": {
                "name": "string",
                "kind": "primitive"
              }
            }
          ],
          "returnType": {
            "name": "void",
            "kind": "primitive"
          }
        },
        "body": [],
        "location": {
          "start": 67,
          "end": 94,
          "file": "modules/std.vader"
        }
      },
      "location": {
        "start": 58,
        "end": 94,
        "file": "modules/std.vader"
      }
    },
    {
      "kind": "VariableDeclarationStatement",
      "name": "length",
      "isConstant": true,
      "type": {
        "kind": "function",
        "decorators": [
          "intrinsic"
        ],
        "parameters": [
          {
            "name": "array",
            "type": {
              "kind": "array",
              "type": {
                "name": "u32",
                "kind": "primitive"
              },
              "dimension": 1
            }
          }
        ],
        "returnType": {
          "name": "u32",
          "kind": "primitive"
        }
      },
      "value": {
        "kind": "FunctionDeclarationExpression",
        "type": {
          "kind": "function",
          "decorators": [
            "intrinsic"
          ],
          "parameters": [
            {
              "name": "array",
              "type": {
                "kind": "array",
                "type": {
                  "name": "u32",
                  "kind": "primitive"
                },
                "dimension": 1
              }
            }
          ],
          "returnType": {
            "name": "u32",
            "kind": "primitive"
          }
        },
        "body": [],
        "location": {
          "start": 117,
          "end": 140,
          "file": "modules/std.vader"
        }
      },
      "location": {
        "start": 107,
        "end": 140,
        "file": "modules/std.vader"
      }
    },
    {
      "kind": "VariableDeclarationStatement",
      "name": "main",
      "isConstant": true,
      "type": {
        "kind": "function",
        "decorators": [],
        "parameters": [],
        "returnType": {
          "name": "void",
          "kind": "primitive"
        }
      },
      "value": {
        "kind": "FunctionDeclarationExpression",
        "type": {
          "kind": "function",
          "decorators": [],
          "parameters": [],
          "returnType": {
            "name": "void",
            "kind": "primitive"
          }
        },
        "body": [
          {
            "kind": "CallExpression",
            "type": {
              "name": "void",
              "kind": "primitive"
            },
            "functionName": "print",
            "parameters": [
              {
                "kind": "StringExpression",
                "type": {
                  "name": "string",
                  "kind": "primitive"
                },
                "value": "Hello world\n",
                "location": {
                  "start": 38,
                  "end": 53,
                  "file": "examples/simple_hello.vader"
                }
              }
            ],
            "location": {
              "start": 32,
              "end": 54,
              "file": "examples/simple_hello.vader"
            }
          }
        ],
        "location": {
          "start": 21,
          "end": 56,
          "file": "examples/simple_hello.vader"
        }
      },
      "location": {
        "start": 13,
        "end": 56,
        "file": "examples/simple_hello.vader"
      }
    }
  ],
  "location": {
    "start": 0,
    "end": 56,
    "file": "examples/simple_hello.vader"
  }
}