{
  "kind": "Program",
  "body": [
    {
      "kind": "VariableDeclarationStatement",
      "name": "file",
      "isConstant": true,
      "type": {
        "kind": "function",
        "decorators": [
          "intrinsic"
        ],
        "parameters": [
          {
            "name": "path",
            "type": {
              "name": "string",
              "kind": "primitive"
            }
          }
        ],
        "returnType": {
          "name": "string",
          "kind": "primitive"
        }
      },
      "value": {
        "kind": "FunctionDeclarationExpression",
        "type": {
          "kind": "function",
          "decorators": [
            "intrinsic"
          ],
          "parameters": [
            {
              "name": "path",
              "type": {
                "name": "string",
                "kind": "primitive"
              }
            }
          ],
          "returnType": {
            "name": "string",
            "kind": "primitive"
          }
        },
        "body": [],
        "location": {
          "start": {
            "offset": 19,
            "line": 2,
            "column": 9
          },
          "end": {
            "offset": 45,
            "line": 2,
            "column": 35
          },
          "file": "modules/std.vader"
        }
      },
      "location": {
        "start": {
          "offset": 11,
          "line": 2,
          "column": 1
        },
        "end": {
          "offset": 45,
          "line": 2,
          "column": 35
        },
        "file": "modules/std.vader"
      }
    },
    {
      "kind": "VariableDeclarationStatement",
      "name": "print",
      "isConstant": true,
      "type": {
        "kind": "function",
        "decorators": [
          "intrinsic"
        ],
        "parameters": [
          {
            "name": "message",
            "type": {
              "name": "string",
              "kind": "primitive"
            }
          }
        ],
        "returnType": {
          "name": "void",
          "kind": "primitive"
        }
      },
      "value": {
        "kind": "FunctionDeclarationExpression",
        "type": {
          "kind": "function",
          "decorators": [
            "intrinsic"
          ],
          "parameters": [
            {
              "name": "message",
              "type": {
                "name": "string",
                "kind": "primitive"
              }
            }
          ],
          "returnType": {
            "name": "void",
            "kind": "primitive"
          }
        },
        "body": [],
        "location": {
          "start": {
            "offset": 67,
            "line": 5,
            "column": 10
          },
          "end": {
            "offset": 94,
            "line": 5,
            "column": 37
          },
          "file": "modules/std.vader"
        }
      },
      "location": {
        "start": {
          "offset": 58,
          "line": 5,
          "column": 1
        },
        "end": {
          "offset": 94,
          "line": 5,
          "column": 37
        },
        "file": "modules/std.vader"
      }
    },
    {
      "kind": "VariableDeclarationStatement",
      "name": "length",
      "isConstant": true,
      "type": {
        "kind": "function",
        "decorators": [
          "intrinsic"
        ],
        "parameters": [
          {
            "name": "array",
            "type": {
              "kind": "array",
              "type": {
                "name": "u32",
                "kind": "primitive"
              },
              "dimension": 1
            }
          }
        ],
        "returnType": {
          "name": "u32",
          "kind": "primitive"
        }
      },
      "value": {
        "kind": "FunctionDeclarationExpression",
        "type": {
          "kind": "function",
          "decorators": [
            "intrinsic"
          ],
          "parameters": [
            {
              "name": "array",
              "type": {
                "kind": "array",
                "type": {
                  "name": "u32",
                  "kind": "primitive"
                },
                "dimension": 1
              }
            }
          ],
          "returnType": {
            "name": "u32",
            "kind": "primitive"
          }
        },
        "body": [],
        "location": {
          "start": {
            "offset": 117,
            "line": 8,
            "column": 11
          },
          "end": {
            "offset": 140,
            "line": 8,
            "column": 34
          },
          "file": "modules/std.vader"
        }
      },
      "location": {
        "start": {
          "offset": 107,
          "line": 8,
          "column": 1
        },
        "end": {
          "offset": 140,
          "line": 8,
          "column": 34
        },
        "file": "modules/std.vader"
      }
    },
    {
      "kind": "VariableDeclarationStatement",
      "name": "return_code",
      "isConstant": false,
      "type": {
        "name": "u32",
        "kind": "primitive",
        "signed": false
      },
      "value": {
        "kind": "NumberExpression",
        "type": {
          "name": "u32",
          "kind": "primitive",
          "signed": false
        },
        "value": 32,
        "location": {
          "start": {
            "offset": 28,
            "line": 3,
            "column": 16
          },
          "end": {
            "offset": 30,
            "line": 3,
            "column": 18
          },
          "file": "examples/hello.vader"
        }
      },
      "location": {
        "start": {
          "offset": 13,
          "line": 3,
          "column": 1
        },
        "end": {
          "offset": 30,
          "line": 3,
          "column": 18
        },
        "file": "examples/hello.vader"
      }
    },
    {
      "kind": "VariableDeclarationStatement",
      "name": "add",
      "isConstant": true,
      "type": {
        "kind": "function",
        "decorators": [],
        "parameters": [
          {
            "name": "a",
            "type": {
              "name": "u32",
              "kind": "primitive"
            }
          }
        ],
        "returnType": {
          "name": "u32",
          "kind": "primitive"
        }
      },
      "value": {
        "kind": "FunctionDeclarationExpression",
        "type": {
          "kind": "function",
          "decorators": [],
          "parameters": [
            {
              "name": "a",
              "type": {
                "name": "u32",
                "kind": "primitive"
              }
            }
          ],
          "returnType": {
            "name": "u32",
            "kind": "primitive"
          }
        },
        "body": [
          {
            "kind": "VariableDeclarationStatement",
            "name": "x",
            "isConstant": false,
            "type": {
              "name": "u32",
              "kind": "primitive",
              "signed": false
            },
            "value": {
              "kind": "NumberExpression",
              "type": {
                "name": "u32",
                "kind": "primitive",
                "signed": false
              },
              "value": 2,
              "location": {
                "start": {
                  "offset": 67,
                  "line": 5,
                  "column": 10
                },
                "end": {
                  "offset": 68,
                  "line": 5,
                  "column": 11
                },
                "file": "examples/hello.vader"
              }
            },
            "location": {
              "start": {
                "offset": 62,
                "line": 5,
                "column": 5
              },
              "end": {
                "offset": 68,
                "line": 5,
                "column": 11
              },
              "file": "examples/hello.vader"
            }
          },
          {
            "kind": "VariableAssignmentStatement",
            "identifier": {
              "kind": "IdentifierExpression",
              "type": {
                "name": "u32",
                "kind": "primitive",
                "signed": false
              },
              "identifier": "x",
              "location": {
                "start": {
                  "offset": 73,
                  "line": 6,
                  "column": 5
                },
                "end": {
                  "offset": 74,
                  "line": 6,
                  "column": 6
                },
                "file": "examples/hello.vader"
              }
            },
            "value": {
              "kind": "BinaryExpression",
              "operator": "+",
              "type": {
                "name": "u32",
                "kind": "primitive",
                "signed": false
              },
              "lhs": {
                "kind": "IdentifierExpression",
                "type": {
                  "name": "u32",
                  "kind": "primitive",
                  "signed": false
                },
                "identifier": "x",
                "location": {
                  "start": {
                    "offset": 77,
                    "line": 6,
                    "column": 9
                  },
                  "end": {
                    "offset": 78,
                    "line": 6,
                    "column": 10
                  },
                  "file": "examples/hello.vader"
                }
              },
              "rhs": {
                "kind": "NumberExpression",
                "type": {
                  "name": "u32",
                  "kind": "primitive",
                  "signed": false
                },
                "value": 1,
                "location": {
                  "start": {
                    "offset": 81,
                    "line": 6,
                    "column": 13
                  },
                  "end": {
                    "offset": 82,
                    "line": 6,
                    "column": 14
                  },
                  "file": "examples/hello.vader"
                }
              },
              "location": {
                "start": {
                  "offset": 77,
                  "line": 6,
                  "column": 9
                },
                "end": {
                  "offset": 82,
                  "line": 6,
                  "column": 14
                },
                "file": "examples/hello.vader"
              }
            },
            "location": {
              "start": {
                "offset": 73,
                "line": 6,
                "column": 5
              },
              "file": "examples/hello.vader",
              "end": {
                "offset": 82,
                "line": 6,
                "column": 14
              }
            }
          },
          {
            "kind": "ReturnStatement",
            "expression": {
              "kind": "BinaryExpression",
              "operator": "+",
              "type": {
                "name": "u32",
                "kind": "primitive"
              },
              "lhs": {
                "kind": "IdentifierExpression",
                "type": {
                  "name": "u32",
                  "kind": "primitive"
                },
                "identifier": "a",
                "location": {
                  "start": {
                    "offset": 94,
                    "line": 7,
                    "column": 12
                  },
                  "end": {
                    "offset": 95,
                    "line": 7,
                    "column": 13
                  },
                  "file": "examples/hello.vader"
                }
              },
              "rhs": {
                "kind": "IdentifierExpression",
                "type": {
                  "name": "u32",
                  "kind": "primitive",
                  "signed": false
                },
                "identifier": "x",
                "location": {
                  "start": {
                    "offset": 98,
                    "line": 7,
                    "column": 16
                  },
                  "end": {
                    "offset": 99,
                    "line": 7,
                    "column": 17
                  },
                  "file": "examples/hello.vader"
                }
              },
              "location": {
                "start": {
                  "offset": 94,
                  "line": 7,
                  "column": 12
                },
                "end": {
                  "offset": 99,
                  "line": 7,
                  "column": 17
                },
                "file": "examples/hello.vader"
              }
            },
            "location": {
              "start": {
                "offset": 87,
                "line": 7,
                "column": 5
              },
              "end": {
                "offset": 99,
                "line": 7,
                "column": 17
              },
              "file": "examples/hello.vader"
            }
          }
        ],
        "location": {
          "start": {
            "offset": 38,
            "line": 4,
            "column": 8
          },
          "end": {
            "offset": 101,
            "line": 8,
            "column": 2
          },
          "file": "examples/hello.vader"
        }
      },
      "location": {
        "start": {
          "offset": 31,
          "line": 4,
          "column": 1
        },
        "end": {
          "offset": 101,
          "line": 8,
          "column": 2
        },
        "file": "examples/hello.vader"
      }
    },
    {
      "kind": "VariableDeclarationStatement",
      "name": "main",
      "isConstant": true,
      "type": {
        "kind": "function",
        "decorators": [],
        "parameters": [],
        "returnType": {
          "name": "u32",
          "kind": "primitive"
        }
      },
      "value": {
        "kind": "FunctionDeclarationExpression",
        "type": {
          "kind": "function",
          "decorators": [],
          "parameters": [],
          "returnType": {
            "name": "u32",
            "kind": "primitive"
          }
        },
        "body": [
          {
            "kind": "CallExpression",
            "type": {
              "name": "void",
              "kind": "primitive"
            },
            "functionName": "print",
            "parameters": [
              {
                "kind": "StringExpression",
                "type": {
                  "name": "string",
                  "kind": "primitive",
                  "signed": false
                },
                "value": "Hello world\n",
                "location": {
                  "start": {
                    "offset": 179,
                    "line": 12,
                    "column": 11
                  },
                  "end": {
                    "offset": 194,
                    "line": 12,
                    "column": 26
                  },
                  "file": "examples/hello.vader"
                }
              }
            ],
            "location": {
              "start": {
                "offset": 173,
                "line": 12,
                "column": 5
              },
              "end": {
                "offset": 195,
                "line": 12,
                "column": 27
              },
              "file": "examples/hello.vader"
            }
          },
          {
            "kind": "CallExpression",
            "type": {
              "name": "void",
              "kind": "primitive"
            },
            "functionName": "print",
            "parameters": [
              {
                "kind": "StringExpression",
                "type": {
                  "name": "string",
                  "kind": "primitive",
                  "signed": false
                },
                "value": "Hello world2\n",
                "location": {
                  "start": {
                    "offset": 206,
                    "line": 13,
                    "column": 11
                  },
                  "end": {
                    "offset": 222,
                    "line": 13,
                    "column": 27
                  },
                  "file": "examples/hello.vader"
                }
              }
            ],
            "location": {
              "start": {
                "offset": 200,
                "line": 13,
                "column": 5
              },
              "end": {
                "offset": 223,
                "line": 13,
                "column": 28
              },
              "file": "examples/hello.vader"
            }
          },
          {
            "kind": "CallExpression",
            "type": {
              "name": "void",
              "kind": "primitive"
            },
            "functionName": "print",
            "parameters": [
              {
                "kind": "StringExpression",
                "type": {
                  "name": "string",
                  "kind": "primitive",
                  "signed": false
                },
                "value": "Hello 3\n",
                "location": {
                  "start": {
                    "offset": 234,
                    "line": 14,
                    "column": 11
                  },
                  "end": {
                    "offset": 245,
                    "line": 14,
                    "column": 22
                  },
                  "file": "examples/hello.vader"
                }
              }
            ],
            "location": {
              "start": {
                "offset": 228,
                "line": 14,
                "column": 5
              },
              "end": {
                "offset": 246,
                "line": 14,
                "column": 23
              },
              "file": "examples/hello.vader"
            }
          },
          {
            "kind": "VariableAssignmentStatement",
            "identifier": {
              "kind": "IdentifierExpression",
              "type": {
                "name": "u32",
                "kind": "primitive",
                "signed": false
              },
              "identifier": "return_code",
              "location": {
                "start": {
                  "offset": 251,
                  "line": 15,
                  "column": 5
                },
                "end": {
                  "offset": 262,
                  "line": 15,
                  "column": 16
                },
                "file": "examples/hello.vader"
              }
            },
            "value": {
              "kind": "NumberExpression",
              "type": {
                "name": "u32",
                "kind": "primitive",
                "signed": false
              },
              "value": 0,
              "location": {
                "start": {
                  "offset": 265,
                  "line": 15,
                  "column": 19
                },
                "end": {
                  "offset": 266,
                  "line": 15,
                  "column": 20
                },
                "file": "examples/hello.vader"
              }
            },
            "location": {
              "start": {
                "offset": 251,
                "line": 15,
                "column": 5
              },
              "file": "examples/hello.vader",
              "end": {
                "offset": 266,
                "line": 15,
                "column": 20
              }
            }
          },
          {
            "kind": "ReturnStatement",
            "expression": {
              "kind": "CallExpression",
              "type": {
                "name": "u32",
                "kind": "primitive"
              },
              "functionName": "add",
              "parameters": [
                {
                  "kind": "IdentifierExpression",
                  "type": {
                    "name": "u32",
                    "kind": "primitive",
                    "signed": false
                  },
                  "identifier": "return_code",
                  "location": {
                    "start": {
                      "offset": 282,
                      "line": 16,
                      "column": 16
                    },
                    "end": {
                      "offset": 293,
                      "line": 16,
                      "column": 27
                    },
                    "file": "examples/hello.vader"
                  }
                }
              ],
              "location": {
                "start": {
                  "offset": 278,
                  "line": 16,
                  "column": 12
                },
                "end": {
                  "offset": 294,
                  "line": 16,
                  "column": 28
                },
                "file": "examples/hello.vader"
              }
            },
            "location": {
              "start": {
                "offset": 271,
                "line": 16,
                "column": 5
              },
              "end": {
                "offset": 294,
                "line": 16,
                "column": 28
              },
              "file": "examples/hello.vader"
            }
          }
        ],
        "location": {
          "start": {
            "offset": 111,
            "line": 10,
            "column": 9
          },
          "end": {
            "offset": 296,
            "line": 17,
            "column": 2
          },
          "file": "examples/hello.vader"
        }
      },
      "location": {
        "start": {
          "offset": 103,
          "line": 10,
          "column": 1
        },
        "end": {
          "offset": 296,
          "line": 17,
          "column": 2
        },
        "file": "examples/hello.vader"
      }
    }
  ],
  "location": {
    "start": 0,
    "end": {
      "offset": 296,
      "line": 17,
      "column": 2
    },
    "file": "examples/hello.vader"
  }
}